ibanlib/README.txt
ibanlib/__init__.py
ibanlib/iban.py
ibanlib/iban_countries.cfg
ibanlib/interfaces.py
ibanlib/test.py
ibanlib-0.0.3.dist-info/LICENSE.txt
ibanlib-0.0.3.dist-info/METADATA
ibanlib-0.0.3.dist-info/WHEEL
ibanlib-0.0.3.dist-info/top_level.txt
ibanlib-0.0.3.dist-info/RECORD
